{"version": 0.6, "generator": "Overpass API 0.7.62.1 084b4234", "osm3s": {"timestamp_osm_base": "2024-11-07T07:05:01Z", "copyright": "The data included in this document is from www.openstreetmap.org. The data is made available under ODbL."}, "elements": [{"type": "node", "id": 26576195, "lat": 21.8774215, "lon": 95.9839956, "tags": {"alt_name": "\u1005\u1005\u103a\u1000\u102d\u102f\u1004\u103a\u1038\u1019\u103c\u102d\u102f\u1037", "capital": "4", "name": "\u1005\u1005\u103a\u1000\u102d\u102f\u1004\u103a\u1038", "name:ca": "Sagaing", "name:de": "Sagaing", "name:en": "Sagaing", "name:es": "Sagaing", "name:et": "Sagaing", "name:fa": "\u0632\u0627\u06af\u0627\u06cc\u0646", "name:fr": "Sagaing", "name:hi": "\u0938\u0917\u093e\u0907\u0902\u0917", "name:hr": "Sagaing", "name:it": "Sagaing", "name:ja": "\u30b5\u30ac\u30a4\u30f3", "name:ko": "\uc0ac\uac00\uc789", "name:la": "Sagain", "name:lt": "Sagainas", "name:my": "\u1005\u1005\u103a\u1000\u102d\u102f\u1004\u103a\u1038", "name:nl": "Sagaing", "name:pl": "Sikong", "name:ru": "\u0421\u0438\u043a\u0430\u0439\u043d", "name:sl": "Sagaing", "name:sv": "Sagaing", "name:th": "\u0e2a\u0e30\u0e01\u0e32\u0e22", "name:uk": "\u0421\u0456\u043a\u0430\u0439\u043d", "name:ur": "\u0633\u0627\u06af\u0627\u06cc\u0646\u06af", "name:vi": "Sagaing", "name:zh": "\u5b9e\u7686", "name:zh-Hant": "\u5be6\u7686", "pcode": "MMR005001701", "place": "city", "population": "300000", "wikidata": "Q1018173", "wikipedia": "en:Sagaing"}}, {"type": "node", "id": 26576218, "lat": 21.9596834, "lon": 96.0948743, "tags": {"alt_name:zh": "\u74e6\u57ce", "capital": "4", "int_name": "Mandalay", "name": "\u1019\u1014\u1039\u1010\u101c\u1031\u1038", "name:cs": "Mandalaj", "name:de": "Mandalay", "name:en": "Mandalay", "name:et": "Mandalay", "name:eu": "Mandalay", "name:fr": "Mandalay", "name:hi": "\u092e\u0902\u0926\u0932\u0948", "name:hr": "Mandalay", "name:ja": "\u30de\u30f3\u30c0\u30ec\u30fc", "name:kn": "\u0cae\u0c82\u0ca6\u0cb2\u0cc8", "name:my": "\u1019\u1014\u1039\u1010\u101c\u1031\u1038", "name:pt": "Mandalay", "name:ru": "\u041c\u0430\u043d\u0434\u0430\u043b\u0430\u0439", "name:sk": "Mandalaj", "name:sl": "Mandalaj", "name:sr": "\u041c\u0430\u043d\u0434\u0430\u043b\u0435\u0458", "name:zh": "\u66fc\u5fb7\u52d2", "pcode": "MMR010000777", "place": "city", "population": "1208099", "wikidata": "Q185518", "wikipedia": "en:Mandalay"}}, {"type": "node", "id": 486081668, "lat": 21.8086154, "lon": 95.9743887}, {"type": "node", "id": 486089003, "lat": 21.8212105, "lon": 95.9724054}, {"type": "node", "id": 486089004, "lat": 21.8210751, "lon": 95.9722079}, {"type": "node", "id": 486089005, "lat": 21.8201747, "lon": 95.9714183}, {"type": "node", "id": 486089006, "lat": 21.8200233, "lon": 95.9712381}, {"type": "node", "id": 486089007, "lat": 21.8199117, "lon": 95.9709806}, {"type": "node", "id": 486089008, "lat": 21.8196169, "lon": 95.9701308}, {"type": "node", "id": 486089009, "lat": 21.8195293, "lon": 95.9698648}, {"type": "node", "id": 486089010, "lat": 21.8193938, "lon": 95.9696244}, {"type": "node", "id": 486089017, "lat": 21.8169954, "lon": 95.966174}, {"type": "node", "id": 486089023, "lat": 21.8168758, "lon": 95.9658307}, {"type": "node", "id": 486089027, "lat": 21.8167563, "lon": 95.9656419}, {"type": "node", "id": 486089035, "lat": 21.8148439, "lon": 95.9632301}, {"type": "node", "id": 486089039, "lat": 21.8146845, "lon": 95.9630069}, {"type": "node", "id": 486089042, "lat": 21.814573, "lon": 95.962758}, {"type": "node", "id": 486089046, "lat": 21.8140391, "lon": 95.9607925}, {"type": "node", "id": 486089055, "lat": 21.8139992, "lon": 95.9605178}, {"type": "node", "id": 3358419909, "lat": 21.8159245, "lon": 95.9645929}, {"type": "node", "id": 3358419961, "lat": 21.8230697, "lon": 95.9747973}, {"type": "node", "id": 3358557196, "lat": 21.8164962, "lon": 95.9653138}, {"type": "node", "id": 3358557227, "lat": 21.8141965, "lon": 95.9613719}, {"type": "node", "id": 3361934678, "lat": 21.8133769, "lon": 95.9586498}, {"type": "node", "id": 3361934679, "lat": 21.822169, "lon": 95.9726563}, {"type": "node", "id": 3361934680, "lat": 21.8229259, "lon": 95.9739008}, {"type": "node", "id": 3361934681, "lat": 21.8193204, "lon": 95.9788575}, {"type": "node", "id": 3361934682, "lat": 21.8182447, "lon": 95.9792438}, {"type": "node", "id": 3361934683, "lat": 21.8158143, "lon": 95.9787288}, {"type": "node", "id": 3361934684, "lat": 21.8132246, "lon": 95.9773555}, {"type": "node", "id": 3361934685, "lat": 21.8136828, "lon": 95.9759607}, {"type": "node", "id": 3361934686, "lat": 21.8069094, "lon": 95.9738579}, {"type": "node", "id": 3361934687, "lat": 21.8057738, "lon": 95.9727206}, {"type": "node", "id": 3361934688, "lat": 21.8057987, "lon": 95.9716424}, {"type": "node", "id": 3361934689, "lat": 21.8088889, "lon": 95.969713}, {"type": "node", "id": 3361934690, "lat": 21.8072282, "lon": 95.9690514}, {"type": "node", "id": 3361934691, "lat": 21.8075868, "lon": 95.9647169}, {"type": "node", "id": 4474300952, "lat": 21.8071674, "lon": 95.9732826}, {"type": "node", "id": 4474300953, "lat": 21.8075808, "lon": 95.971786}, {"type": "node", "id": 4474300954, "lat": 21.8089042, "lon": 95.9566583}, {"type": "node", "id": 4474300955, "lat": 21.8089853, "lon": 95.9576011}, {"type": "node", "id": 4474300956, "lat": 21.80905, "lon": 95.9735348}, {"type": "node", "id": 4474300957, "lat": 21.8092841, "lon": 95.9647921}, {"type": "node", "id": 4474300958, "lat": 21.8092891, "lon": 95.9693505}, {"type": "node", "id": 4474300959, "lat": 21.8092933, "lon": 95.9587245}, {"type": "node", "id": 4474300960, "lat": 21.8093153, "lon": 95.9643643}, {"type": "node", "id": 4474300961, "lat": 21.8094367, "lon": 95.9595227}, {"type": "node", "id": 4474300962, "lat": 21.8094736, "lon": 95.9603349}, {"type": "node", "id": 4474300963, "lat": 21.8094816, "lon": 95.9611245}, {"type": "node", "id": 4474300964, "lat": 21.8095244, "lon": 95.9631788}, {"type": "node", "id": 4474300969, "lat": 21.8107907, "lon": 95.9571156}, {"type": "node", "id": 4474300971, "lat": 21.8108729, "lon": 95.9576199}, {"type": "node", "id": 4474300992, "lat": 21.8137497, "lon": 95.9586741}, {"type": "node", "id": 4474300993, "lat": 21.8140167, "lon": 95.9590673}, {"type": "node", "id": 4474300994, "lat": 21.8141267, "lon": 95.9595608}, {"type": "node", "id": 4474301019, "lat": 21.8173175, "lon": 95.966563}, {"type": "node", "id": 4474301023, "lat": 21.8178335, "lon": 95.9663403}, {"type": "node", "id": 4474301041, "lat": 21.8183331, "lon": 95.9672577}, {"type": "node", "id": 4474301045, "lat": 21.8197552, "lon": 95.9791151}, {"type": "node", "id": 4474301046, "lat": 21.819762, "lon": 95.9787846}, {"type": "node", "id": 4474301047, "lat": 21.8199096, "lon": 95.9792546}, {"type": "node", "id": 4474301048, "lat": 21.8203129, "lon": 95.979614}, {"type": "node", "id": 4474301049, "lat": 21.8209404, "lon": 95.978745}, {"type": "node", "id": 4474301050, "lat": 21.8210891, "lon": 95.9783233}, {"type": "node", "id": 4474301051, "lat": 21.8215082, "lon": 95.9767574}, {"type": "node", "id": 4474301052, "lat": 21.8222382, "lon": 95.9754568}, {"type": "way", "id": 329326672, "nodes": [4474300954, 4474300969, 4474300971, 3361934678, 4474300992, 4474300993, 4474300994, 486089055, 486089046, 3358557227, 486089042, 486089039, 486089035, 3358419909, 3358557196, 486089027, 486089023, 486089017, 4474301019, 4474301023, 4474301041, 486089010, 486089009, 486089008, 486089007, 486089006, 486089005, 486089004, 486089003, 3361934679, 3361934680, 3358419961, 4474301052, 4474301051, 4474301050, 4474301049, 4474301048, 4474301047, 4474301045, 4474301046, 3361934681, 3361934682, 3361934683, 3361934684, 3361934685, 486081668, 3361934686, 3361934687, 3361934688, 4474300953, 4474300952, 4474300956, 4474300958, 3361934689, 3361934690, 3361934691, 4474300957, 4474300960, 4474300964, 4474300963, 4474300962, 4474300961, 4474300959, 4474300955, 4474300954], "tags": {"landuse": "residential", "name": "Tada-U", "place": "city"}}]}